<?xml version="1.0" encoding="utf-8"?>
<!DOCTYPE LocRefs SYSTEM "../../../../dtd/locrefs.dtd">
<LocRefs ver="2.1.2.9" pubno="EM25T2E" xml:lang="en">
  <connector code="a1" type="conn" subcode="">
    <location code="WR014" />
    <location code="WR016" />
  </connector>
  <connector code="A1" type="conn" subcode="">
    <location code="WR001" />
  </connector>
  <connector code="A2" type="conn" subcode="">
    <location code="WR001" />
  </connector>
  <connector code="A3" type="conn" subcode="">
    <location code="WR001" />
  </connector>
  <connector code="A4" type="conn" subcode="">
    <location code="WR001" />
  </connector>
  <connector code="A5" type="conn" subcode="">
    <location code="WR001" />
  </connector>
  <connector code="A7" type="conn" subcode="">
    <location code="WR001" />
  </connector>
  <connector code="A10" type="conn" subcode="">
    <location code="WR001" />
  </connector>
  <connector code="A11" type="conn" subcode="">
    <location code="WR001" />
  </connector>
  <connector code="A13" type="conn" subcode="">
    <location code="WR001" />
  </connector>
  <connector code="A14" type="conn" subcode="">
    <location code="WR001" />
  </connector>
  <connector code="A15" type="conn" subcode="">
    <location code="WR001" />
  </connector>
  <connector code="A17" type="conn" subcode="">
    <location code="WR001" />
  </connector>
  <connector code="A20" type="conn" subcode="">
    <location code="WR001" />
  </connector>
  <connector code="A21" type="conn" subcode="">
    <location code="WR001" />
  </connector>
  <connector code="A22" type="conn" subcode="">
    <location code="WR001" />
  </connector>
  <connector code="A23" type="conn" subcode="">
    <location code="WR001" />
  </connector>
  <connector code="A24" type="conn" subcode="">
    <location code="WR001" />
  </connector>
  <connector code="A25" type="conn" subcode="">
    <location code="WR001" />
  </connector>
  <connector code="A26" type="conn" subcode="">
    <location code="WR001" />
  </connector>
  <connector code="A27" type="conn" subcode="">
    <location code="WR001" />
  </connector>
  <connector code="A28" type="conn" subcode="">
    <location code="WR001" />
  </connector>
  <connector code="A35" type="conn" subcode="">
    <location code="WR001" />
  </connector>
  <connector code="A36" type="conn" subcode="">
    <location code="WR001" />
  </connector>
  <connector code="A38" type="conn" subcode="">
    <location code="WR001" />
  </connector>
  <connector code="A40" type="conn" subcode="">
    <location code="WR001" />
  </connector>
  <connector code="A42" type="conn" subcode="">
    <location code="WR001" />
  </connector>
  <connector code="A43" type="conn" subcode="">
    <location code="WR001" />
  </connector>
  <connector code="b1" type="conn" subcode="">
    <location code="WR014" />
    <location code="WR016" />
  </connector>
  <connector code="B1" type="conn" subcode="">
    <location code="WR001" />
  </connector>
  <connector code="B2" type="conn" subcode="">
    <location code="WR001" />
  </connector>
  <connector code="b3" type="conn" subcode="">
    <location code="WR014" />
    <location code="WR016" />
  </connector>
  <connector code="B3" type="conn" subcode="">
    <location code="WR001" />
  </connector>
  <connector code="b4" type="conn" subcode="">
    <location code="WR014" />
    <location code="WR016" />
  </connector>
  <connector code="c1" type="conn" subcode="">
    <location code="WR014" />
    <location code="WR016" />
  </connector>
  <connector code="C1" type="conn" subcode="">
    <location code="WR002" />
  </connector>
  <connector code="c2" type="conn" subcode="">
    <location code="WR014" />
    <location code="WR016" />
  </connector>
  <connector code="C2" type="conn" subcode="">
    <location code="WR002" />
  </connector>
  <connector code="C3" type="conn" subcode="">
    <location code="WR002" />
  </connector>
  <connector code="C4" type="conn" subcode="">
    <location code="WR002" />
  </connector>
  <connector code="C5" type="conn" subcode="">
    <location code="WR002" />
  </connector>
  <connector code="C6" type="conn" subcode="">
    <location code="WR002" />
  </connector>
  <connector code="C7" type="conn" subcode="">
    <location code="WR002" />
  </connector>
  <connector code="C8" type="conn" subcode="">
    <location code="WR002" />
  </connector>
  <connector code="C9" type="conn" subcode="">
    <location code="WR002" />
  </connector>
  <connector code="C10" type="conn" subcode="">
    <location code="WR002" />
  </connector>
  <connector code="C11" type="conn" subcode="">
    <location code="WR002" />
  </connector>
  <connector code="C12" type="conn" subcode="">
    <location code="WR002" />
  </connector>
  <connector code="C13" type="conn" subcode="">
    <location code="WR002" />
  </connector>
  <connector code="C14" type="conn" subcode="">
    <location code="WR002" />
  </connector>
  <connector code="C15" type="conn" subcode="">
    <location code="WR002" />
  </connector>
  <connector code="C16" type="conn" subcode="">
    <location code="WR002" />
  </connector>
  <connector code="C17" type="conn" subcode="">
    <location code="WR002" />
  </connector>
  <connector code="C18" type="conn" subcode="">
    <location code="WR002" />
  </connector>
  <connector code="C19" type="conn" subcode="">
    <location code="WR002" />
  </connector>
  <connector code="C20" type="conn" subcode="">
    <location code="WR002" />
  </connector>
  <connector code="C21" type="conn" subcode="">
    <location code="WR002" />
  </connector>
  <connector code="C22" type="conn" subcode="">
    <location code="WR002" />
  </connector>
  <connector code="C23" type="conn" subcode="">
    <location code="WR002" />
  </connector>
  <connector code="C24" type="conn" subcode="">
    <location code="WR002" />
  </connector>
  <connector code="C25" type="conn" subcode="">
    <location code="WR002" />
  </connector>
  <connector code="C26" type="conn" subcode="">
    <location code="WR002" />
  </connector>
  <connector code="C27" type="conn" subcode="">
    <location code="WR002" />
  </connector>
  <connector code="C28" type="conn" subcode="">
    <location code="WR002" />
  </connector>
  <connector code="C29" type="conn" subcode="">
    <location code="WR002" />
  </connector>
  <connector code="C30" type="conn" subcode="">
    <location code="WR002" />
  </connector>
  <connector code="C31" type="conn" subcode="">
    <location code="WR002" />
  </connector>
  <connector code="C32" type="conn" subcode="">
    <location code="WR002" />
  </connector>
  <connector code="C35" type="conn" subcode="">
    <location code="WR002" />
  </connector>
  <connector code="C36" type="conn" subcode="">
    <location code="WR002" />
  </connector>
  <connector code="C37" type="conn" subcode="">
    <location code="WR002" />
  </connector>
  <connector code="C38" type="conn" subcode="">
    <location code="WR002" />
  </connector>
  <connector code="C39" type="conn" subcode="">
    <location code="WR002" />
  </connector>
  <connector code="C96" type="conn" subcode="">
    <location code="WR002" />
  </connector>
  <connector code="C97" type="conn" subcode="">
    <location code="WR002" />
  </connector>
  <connector code="C104" type="conn" subcode="">
    <location code="WR002" />
  </connector>
  <connector code="C105" type="conn" subcode="">
    <location code="WR002" />
  </connector>
  <connector code="d1" type="conn" subcode="">
    <location code="WR014" />
    <location code="WR016" />
  </connector>
  <connector code="D1" type="conn" subcode="">
    <location code="WR003" />
  </connector>
  <connector code="D2" type="conn" subcode="">
    <location code="WR003" />
  </connector>
  <connector code="D3" type="conn" subcode="">
    <location code="WR003" />
  </connector>
  <connector code="D4" type="conn" subcode="">
    <location code="WR003" />
  </connector>
  <connector code="D8" type="conn" subcode="">
    <location code="WR003" />
  </connector>
  <connector code="D9" type="conn" subcode="">
    <location code="WR003" />
  </connector>
  <connector code="e1" type="conn" subcode="">
    <location code="WR014" />
    <location code="WR016" />
  </connector>
  <connector code="f1" type="conn" subcode="">
    <location code="WR014" />
    <location code="WR016" />
  </connector>
  <connector code="h1" type="conn" subcode="">
    <location code="WR003" />
  </connector>
  <connector code="h2" type="conn" subcode="">
    <location code="WR003" />
  </connector>
  <connector code="i1" type="conn" subcode="">
    <location code="WR014" />
    <location code="WR016" />
    <location code="WR018" />
    <location code="WR020" />
  </connector>
  <connector code="I2" type="conn" subcode="">
    <location code="WR003" />
  </connector>
  <connector code="I4" type="conn" subcode="">
    <location code="WR003" />
  </connector>
  <connector code="I5" type="conn" subcode="">
    <location code="WR011" />
  </connector>
  <connector code="I7" type="conn" subcode="">
    <location code="WR011" />
  </connector>
  <connector code="I8" type="conn" subcode="">
    <location code="WR011" />
  </connector>
  <connector code="I9" type="conn" subcode="">
    <location code="WR011" />
  </connector>
  <connector code="I11" type="conn" subcode="">
    <location code="WR011" />
  </connector>
  <connector code="I12" type="conn" subcode="">
    <location code="WR011" />
  </connector>
  <connector code="I13" type="conn" subcode="">
    <location code="WR011" />
  </connector>
  <connector code="I14" type="conn" subcode="">
    <location code="WR011" />
  </connector>
  <connector code="I15" type="conn" subcode="">
    <location code="WR011" />
  </connector>
  <connector code="I16" type="conn" subcode="">
    <location code="WR011" />
  </connector>
  <connector code="I17" type="conn" subcode="">
    <location code="WR011" />
  </connector>
  <connector code="I19" type="conn" subcode="">
    <location code="WR011" />
  </connector>
  <connector code="I20" type="conn" subcode="">
    <location code="WR011" />
  </connector>
  <connector code="I21" type="conn" subcode="">
    <location code="WR011" />
  </connector>
  <connector code="I24" type="conn" subcode="">
    <location code="WR011" />
  </connector>
  <connector code="I25" type="conn" subcode="">
    <location code="WR003" />
  </connector>
  <connector code="I26" type="conn" subcode="">
    <location code="WR011" />
  </connector>
  <connector code="I28" type="conn" subcode="">
    <location code="WR011" />
  </connector>
  <connector code="I36" type="conn" subcode="">
    <location code="WR003" />
  </connector>
  <connector code="I38" type="conn" subcode="">
    <location code="WR003" />
  </connector>
  <connector code="I40" type="conn" subcode="">
    <location code="WR003" />
  </connector>
  <connector code="I42" type="conn" subcode="">
    <location code="WR011" />
  </connector>
  <connector code="I43" type="conn" subcode="">
    <location code="WR011" />
  </connector>
  <connector code="I44" type="conn" subcode="">
    <location code="WR003" />
  </connector>
  <connector code="I45" type="conn" subcode="">
    <location code="WR011" />
  </connector>
  <connector code="I48" type="conn" subcode="">
    <location code="WR003" />
  </connector>
  <connector code="I49" type="conn" subcode="">
    <location code="WR011" />
  </connector>
  <connector code="I50" type="conn" subcode="">
    <location code="WR011" />
  </connector>
  <connector code="I51" type="conn" subcode="">
    <location code="WR011" />
  </connector>
  <connector code="I52" type="conn" subcode="">
    <location code="WR003" />
  </connector>
  <connector code="I54" type="conn" subcode="">
    <location code="WR011" />
  </connector>
  <connector code="I56" type="conn" subcode="">
    <location code="WR011" />
  </connector>
  <connector code="I67" type="conn" subcode="">
    <location code="WR011" />
  </connector>
  <connector code="I68" type="conn" subcode="">
    <location code="WR011" />
  </connector>
  <connector code="I69" type="conn" subcode="">
    <location code="WR011" />
  </connector>
  <connector code="I70" type="conn" subcode="">
    <location code="WR011" />
  </connector>
  <connector code="I71" type="conn" subcode="">
    <location code="WR011" />
  </connector>
  <connector code="I72" type="conn" subcode="">
    <location code="WR011" />
  </connector>
  <connector code="I73" type="conn" subcode="">
    <location code="WR011" />
  </connector>
  <connector code="I75" type="conn" subcode="">
    <location code="WR011" />
  </connector>
  <connector code="I76" type="conn" subcode="">
    <location code="WR003" />
  </connector>
  <connector code="I77" type="conn" subcode="">
    <location code="WR011" />
    <location code="RL012" ttl="RL002" />
    <location code="RL017" ttl="RL003" />
  </connector>
  <connector code="I78" type="conn" subcode="">
    <location code="WR011" />
    <location code="RL012" ttl="RL002" />
    <location code="RL017" ttl="RL003" />
  </connector>
  <connector code="I79" type="conn" subcode="">
    <location code="WR011" />
    <location code="RL012" ttl="RL002" />
    <location code="RL017" ttl="RL003" />
  </connector>
  <connector code="I80" type="conn" subcode="">
    <location code="WR011" />
    <location code="RL013" ttl="RL002" />
    <location code="RL018" ttl="RL003" />
  </connector>
  <connector code="I81" type="conn" subcode="">
    <location code="RL013" ttl="RL002" />
    <location code="RL018" ttl="RL003" />
  </connector>
  <connector code="I82" type="conn" subcode="">
    <location code="WR011" />
    <location code="RL013" ttl="RL002" />
    <location code="RL018" ttl="RL003" />
  </connector>
  <connector code="I83" type="conn" subcode="">
    <location code="RL012" ttl="RL002" />
    <location code="RL017" ttl="RL003" />
  </connector>
  <connector code="I84" type="conn" subcode="">
    <location code="WR003" />
  </connector>
  <connector code="I86" type="conn" subcode="">
    <location code="WR003" />
  </connector>
  <connector code="I87" type="conn" subcode="">
    <location code="WR011" />
  </connector>
  <connector code="I88" type="conn" subcode="">
    <location code="WR011" />
  </connector>
  <connector code="I91" type="conn" subcode="">
    <location code="WR003" />
  </connector>
  <connector code="I92" type="conn" subcode="">
    <location code="WR011" />
  </connector>
  <connector code="I93" type="conn" subcode="">
    <location code="WR011" />
  </connector>
  <connector code="I94" type="conn" subcode="">
    <location code="WR011" />
  </connector>
  <connector code="I95" type="conn" subcode="">
    <location code="WR011" />
  </connector>
  <connector code="I96" type="conn" subcode="">
    <location code="WR011" />
  </connector>
  <connector code="I97" type="conn" subcode="">
    <location code="WR011" />
  </connector>
  <connector code="I98" type="conn" subcode="">
    <location code="WR011" />
  </connector>
  <connector code="I99" type="conn" subcode="">
    <location code="WR011" />
  </connector>
  <connector code="I100" type="conn" subcode="">
    <location code="WR011" />
    <location code="RL012" ttl="RL002" />
    <location code="RL017" ttl="RL003" />
  </connector>
  <connector code="I101" type="conn" subcode="">
    <location code="WR011" />
    <location code="RL013" ttl="RL002" />
    <location code="RL018" ttl="RL003" />
  </connector>
  <connector code="I117" type="conn" subcode="">
    <location code="WR011" />
  </connector>
  <connector code="I118" type="conn" subcode="">
    <location code="WR011" />
  </connector>
  <connector code="I119" type="conn" subcode="">
    <location code="WR011" />
  </connector>
  <connector code="I120" type="conn" subcode="">
    <location code="WR011" />
  </connector>
  <connector code="I121" type="conn" subcode="">
    <location code="WR011" />
  </connector>
  <connector code="I122" type="conn" subcode="">
    <location code="WR011" />
  </connector>
  <connector code="I123" type="conn" subcode="">
    <location code="WR011" />
  </connector>
  <connector code="I124" type="conn" subcode="">
    <location code="WR011" />
  </connector>
  <connector code="j1" type="conn" subcode="">
    <location code="WR014" />
    <location code="WR016" />
    <location code="WR018" />
    <location code="WR020" />
  </connector>
  <connector code="J1" type="conn" subcode="">
    <location code="WR003" />
  </connector>
  <connector code="J2" type="conn" subcode="">
    <location code="WR003" />
  </connector>
  <connector code="k1" type="conn" subcode="">
    <location code="WR003" />
  </connector>
  <connector code="k2" type="conn" subcode="">
    <location code="WR003" />
  </connector>
  <connector code="L1" type="conn" subcode="">
    <location code="WR012" />
  </connector>
  <connector code="L2" type="conn" subcode="">
    <location code="WR012" />
  </connector>
  <connector code="L3" type="conn" subcode="">
    <location code="WR012" />
  </connector>
  <connector code="L4" type="conn" subcode="">
    <location code="WR012" />
  </connector>
  <connector code="L5" type="conn" subcode="">
    <location code="WR012" />
  </connector>
  <connector code="L6" type="conn" subcode="">
    <location code="WR012" />
  </connector>
  <connector code="L7" type="conn" subcode="">
    <location code="WR012" />
  </connector>
  <connector code="L8" type="conn" subcode="">
    <location code="WR012" />
  </connector>
  <connector code="L9" type="conn" subcode="">
    <location code="WR012" />
  </connector>
  <connector code="L10" type="conn" subcode="">
    <location code="WR012" />
  </connector>
  <connector code="L12" type="conn" subcode="">
    <location code="WR012" />
  </connector>
  <connector code="L13" type="conn" subcode="">
    <location code="WR012" />
  </connector>
  <connector code="L14" type="conn" subcode="">
    <location code="WR012" />
  </connector>
  <connector code="L15" type="conn" subcode="">
    <location code="WR012" />
  </connector>
  <connector code="L16" type="conn" subcode="">
    <location code="WR012" />
  </connector>
  <connector code="L17" type="conn" subcode="">
    <location code="WR012" />
  </connector>
  <connector code="L18" type="conn" subcode="">
    <location code="WR012" />
  </connector>
  <connector code="L19" type="conn" subcode="">
    <location code="WR012" />
  </connector>
  <connector code="L20" type="conn" subcode="">
    <location code="WR012" />
  </connector>
  <connector code="L21" type="conn" subcode="">
    <location code="WR012" />
  </connector>
  <connector code="L22" type="conn" subcode="">
    <location code="WR012" />
  </connector>
  <connector code="L23" type="conn" subcode="">
    <location code="WR012" />
  </connector>
  <connector code="L24" type="conn" subcode="">
    <location code="WR012" />
  </connector>
  <connector code="L25" type="conn" subcode="">
    <location code="WR012" />
  </connector>
  <connector code="L26" type="conn" subcode="">
    <location code="WR012" />
  </connector>
  <connector code="L27" type="conn" subcode="">
    <location code="WR012" />
  </connector>
  <connector code="L28" type="conn" subcode="">
    <location code="WR012" />
  </connector>
  <connector code="L29" type="conn" subcode="">
    <location code="WR012" />
  </connector>
  <connector code="L30" type="conn" subcode="">
    <location code="WR012" />
  </connector>
  <connector code="L31" type="conn" subcode="">
    <location code="WR012" />
  </connector>
  <connector code="L34" type="conn" subcode="">
    <location code="WR012" />
  </connector>
  <connector code="L36" type="conn" subcode="">
    <location code="WR012" />
  </connector>
  <connector code="L37" type="conn" subcode="">
    <location code="WR012" />
  </connector>
  <connector code="L38" type="conn" subcode="">
    <location code="WR012" />
  </connector>
  <connector code="L39" type="conn" subcode="">
    <location code="WR012" />
  </connector>
  <connector code="L40" type="conn" subcode="">
    <location code="WR012" />
  </connector>
  <connector code="L41" type="conn" subcode="">
    <location code="WR012" />
  </connector>
  <connector code="L42" type="conn" subcode="">
    <location code="WR012" />
  </connector>
  <connector code="L43" type="conn" subcode="">
    <location code="WR012" />
  </connector>
  <connector code="L44" type="conn" subcode="">
    <location code="WR012" />
  </connector>
  <connector code="L45" type="conn" subcode="">
    <location code="WR012" />
  </connector>
  <connector code="L46" type="conn" subcode="">
    <location code="WR012" />
  </connector>
  <connector code="L47" type="conn" subcode="">
    <location code="WR012" />
  </connector>
  <connector code="L49" type="conn" subcode="">
    <location code="WR012" />
  </connector>
  <connector code="L50" type="conn" subcode="">
    <location code="WR012" />
  </connector>
  <connector code="L52" type="conn" subcode="">
    <location code="WR012" />
  </connector>
  <connector code="L53" type="conn" subcode="">
    <location code="WR012" />
  </connector>
  <connector code="L54" type="conn" subcode="">
    <location code="WR012" />
  </connector>
  <connector code="L55" type="conn" subcode="">
    <location code="WR012" />
  </connector>
  <connector code="L56" type="conn" subcode="">
    <location code="WR012" />
  </connector>
  <connector code="L57" type="conn" subcode="">
    <location code="WR012" />
  </connector>
  <connector code="L58" type="conn" subcode="">
    <location code="WR012" />
  </connector>
  <connector code="m1" type="conn" subcode="">
    <location code="WR003" />
  </connector>
  <connector code="M1" type="conn" subcode="">
    <location code="WR012" />
  </connector>
  <connector code="m2" type="conn" subcode="">
    <location code="WR003" />
  </connector>
  <connector code="m3" type="conn" subcode="">
    <location code="WR003" />
  </connector>
  <connector code="m4" type="conn" subcode="">
    <location code="WR003" />
  </connector>
  <connector code="N1" type="conn" subcode="">
    <location code="WR012" />
  </connector>
  <connector code="O2" type="conn" subcode="">
    <location code="WR013" />
    <location code="WR015" />
    <location code="WR017" />
    <location code="WR019" />
  </connector>
  <connector code="O3" type="conn" subcode="">
    <location code="WR013" />
    <location code="WR015" />
    <location code="WR017" />
    <location code="WR019" />
  </connector>
  <connector code="O10" type="conn" subcode="">
    <location code="WR013" />
    <location code="WR015" />
    <location code="WR017" />
    <location code="WR019" />
  </connector>
  <connector code="O11" type="conn" subcode="">
    <location code="WR015" />
  </connector>
  <connector code="P2" type="conn" subcode="">
    <location code="WR013" />
    <location code="WR015" />
    <location code="WR017" />
    <location code="WR019" />
  </connector>
  <connector code="P3" type="conn" subcode="">
    <location code="WR015" />
    <location code="WR019" />
  </connector>
  <connector code="P4" type="conn" subcode="">
    <location code="WR015" />
    <location code="WR019" />
  </connector>
  <connector code="P5" type="conn" subcode="">
    <location code="WR013" />
    <location code="WR017" />
  </connector>
  <connector code="P6" type="conn" subcode="">
    <location code="WR015" />
    <location code="WR019" />
  </connector>
  <connector code="P7" type="conn" subcode="">
    <location code="WR013" />
    <location code="WR015" />
    <location code="WR017" />
    <location code="WR019" />
  </connector>
  <connector code="P8" type="conn" subcode="">
    <location code="WR013" />
    <location code="WR017" />
  </connector>
  <connector code="P9" type="conn" subcode="">
    <location code="WR013" />
    <location code="WR017" />
  </connector>
  <connector code="P10" type="conn" subcode="">
    <location code="WR015" />
    <location code="WR019" />
  </connector>
  <connector code="Q1" type="conn" subcode="">
    <location code="WR013" />
    <location code="WR017" />
  </connector>
  <connector code="Q2" type="conn" subcode="">
    <location code="WR013" />
    <location code="WR017" />
  </connector>
  <connector code="Q3" type="conn" subcode="">
    <location code="WR013" />
    <location code="WR017" />
  </connector>
  <connector code="R1" type="conn" subcode="">
    <location code="WR013" />
    <location code="WR017" />
  </connector>
  <connector code="R2" type="conn" subcode="">
    <location code="WR013" />
    <location code="WR017" />
  </connector>
  <connector code="R3" type="conn" subcode="">
    <location code="WR013" />
    <location code="WR017" />
  </connector>
  <connector code="s1" type="conn" subcode="">
    <location code="WR003" />
  </connector>
  <connector code="S10" type="conn" subcode="">
    <location code="WR013" />
    <location code="WR017" />
  </connector>
  <connector code="S11" type="conn" subcode="">
    <location code="WR013" />
    <location code="WR015" />
  </connector>
  <connector code="S13" type="conn" subcode="">
    <location code="WR013" />
    <location code="WR017" />
  </connector>
  <connector code="S14" type="conn" subcode="">
    <location code="WR013" />
  </connector>
  <connector code="S15" type="conn" subcode="">
    <location code="WR013" />
    <location code="WR015" />
    <location code="WR017" />
    <location code="WR020" />
  </connector>
  <connector code="S16" type="conn" subcode="">
    <location code="WR017" />
  </connector>
  <connector code="S17" type="conn" subcode="">
    <location code="WR013" />
  </connector>
  <connector code="s2" type="conn" subcode="">
    <location code="WR003" />
  </connector>
  <connector code="S2" type="conn" subcode="">
    <location code="WR013" />
    <location code="WR015" />
    <location code="WR017" />
    <location code="WR020" />
  </connector>
  <connector code="S3" type="conn" subcode="">
    <location code="WR013" />
    <location code="WR015" />
    <location code="WR017" />
    <location code="WR020" />
  </connector>
  <connector code="S4" type="conn" subcode="">
    <location code="WR013" />
    <location code="WR015" />
    <location code="WR017" />
    <location code="WR020" />
  </connector>
  <connector code="S5" type="conn" subcode="">
    <location code="WR013" />
    <location code="WR015" />
    <location code="WR017" />
  </connector>
  <connector code="S6" type="conn" subcode="">
    <location code="WR020" />
  </connector>
  <connector code="S7" type="conn" subcode="">
    <location code="WR020" />
  </connector>
  <connector code="S8" type="conn" subcode="">
    <location code="WR020" />
  </connector>
  <connector code="S9" type="conn" subcode="">
    <location code="WR013" />
    <location code="WR015" />
  </connector>
  <connector code="S30" type="conn" subcode="">
    <location code="WR020" />
  </connector>
  <connector code="t1" type="conn" subcode="">
    <location code="WR003" />
  </connector>
  <connector code="T1" type="conn" subcode="">
    <location code="WR014" />
    <location code="WR015" />
  </connector>
  <connector code="T3" type="conn" subcode="">
    <location code="WR015" />
    <location code="WR020" />
  </connector>
  <connector code="T4" type="conn" subcode="">
    <location code="WR015" />
    <location code="WR020" />
  </connector>
  <connector code="T5" type="conn" subcode="">
    <location code="WR014" />
    <location code="WR015" />
  </connector>
  <connector code="T6" type="conn" subcode="">
    <location code="WR014" />
    <location code="WR015" />
  </connector>
  <connector code="T7" type="conn" subcode="">
    <location code="WR014" />
    <location code="WR015" />
  </connector>
  <connector code="T8" type="conn" subcode="">
    <location code="WR014" />
    <location code="WR018" />
  </connector>
  <connector code="T9" type="conn" subcode="">
    <location code="WR014" />
    <location code="WR018" />
  </connector>
  <connector code="T10" type="conn" subcode="">
    <location code="WR014" />
    <location code="WR015" />
    <location code="WR018" />
    <location code="WR020" />
  </connector>
  <connector code="T11" type="conn" subcode="">
    <location code="WR018" />
    <location code="WR020" />
  </connector>
  <connector code="T12" type="conn" subcode="">
    <location code="WR018" />
    <location code="WR020" />
  </connector>
  <connector code="T13" type="conn" subcode="">
    <location code="WR018" />
    <location code="WR020" />
  </connector>
  <connector code="T14" type="conn" subcode="">
    <location code="WR018" />
    <location code="WR020" />
  </connector>
  <connector code="T15" type="conn" subcode="">
    <location code="WR018" />
    <location code="WR020" />
  </connector>
  <connector code="T16" type="conn" subcode="">
    <location code="WR018" />
    <location code="WR020" />
  </connector>
  <connector code="T17" type="conn" subcode="">
    <location code="WR018" />
    <location code="WR020" />
  </connector>
  <connector code="T18" type="conn" subcode="">
    <location code="WR018" />
    <location code="WR020" />
  </connector>
  <connector code="T19" type="conn" subcode="">
    <location code="WR014" />
    <location code="WR018" />
  </connector>
  <connector code="U1" type="conn" subcode="">
    <location code="WR014" />
    <location code="WR016" />
    <location code="WR018" />
  </connector>
  <connector code="U2" type="conn" subcode="">
    <location code="WR018" />
  </connector>
  <connector code="U3" type="conn" subcode="">
    <location code="WR014" />
  </connector>
  <connector code="U4" type="conn" subcode="">
    <location code="WR014" />
  </connector>
  <connector code="U5" type="conn" subcode="">
    <location code="WR014" />
    <location code="WR016" />
  </connector>
  <connector code="U6" type="conn" subcode="">
    <location code="WR014" />
  </connector>
  <connector code="V1" type="conn" subcode="">
    <location code="WR014" />
    <location code="WR016" />
    <location code="WR018" />
    <location code="WR020" />
  </connector>
  <connector code="V2" type="conn" subcode="">
    <location code="WR014" />
    <location code="WR016" />
    <location code="WR018" />
    <location code="WR020" />
  </connector>
  <connector code="V3" type="conn" subcode="">
    <location code="WR014" />
    <location code="WR016" />
    <location code="WR018" />
    <location code="WR020" />
  </connector>
  <connector code="W1" type="conn" subcode="">
    <location code="WR016" />
    <location code="WR020" />
  </connector>
  <connector code="W2" type="conn" subcode="">
    <location code="WR016" />
    <location code="WR020" />
  </connector>
  <connector code="X1" type="conn" subcode="">
    <location code="WR016" />
    <location code="WR020" />
  </connector>
  <connector code="X2" type="conn" subcode="">
    <location code="WR016" />
    <location code="WR020" />
  </connector>
  <connector code="Y1" type="conn" subcode="">
    <location code="WR016" />
  </connector>
  <connector code="Y2" type="conn" subcode="">
    <location code="WR016" />
  </connector>
  <connector code="Y3" type="conn" subcode="">
    <location code="WR014" />
    <location code="WR016" />
  </connector>
  <connector code="Y4" type="conn" subcode="">
    <location code="WR014" />
    <location code="WR016" />
  </connector>
  <connector code="Y5" type="conn" subcode="">
    <location code="WR016" />
    <location code="WR018" />
  </connector>
  <connector code="Y6" type="conn" subcode="">
    <location code="WR014" />
  </connector>
  <connector code="Y7" type="conn" subcode="">
    <location code="WR018" />
  </connector>
  <connector code="z1" type="conn" subcode="">
    <location code="WR012" />
  </connector>
  <connector code="z2" type="conn" subcode="">
    <location code="WR012" />
  </connector>
  <connector code="z3" type="conn" subcode="">
    <location code="WR012" />
  </connector>
  <connector code="AI1" type="w2w">
    <location code="WR049" />
  </connector>
  <connector code="AI3" type="w2w">
    <location code="WR049" />
  </connector>
  <connector code="AI4" type="w2w">
    <location code="WR049" />
  </connector>
  <connector code="AI5" type="w2w">
    <location code="WR049" />
  </connector>
  <connector code="AI6" type="w2w">
    <location code="WR049" />
  </connector>
  <connector code="AI7" type="w2w">
    <location code="WR049" />
  </connector>
  <connector code="aS1" type="w2w">
    <location code="WR051" />
    <location code="WR053" />
  </connector>
  <connector code="aS2" type="w2w">
    <location code="WR051" />
    <location code="WR053" />
  </connector>
  <connector code="aS3" type="w2w">
    <location code="WR053" />
  </connector>
  <connector code="bf1" type="w2w">
    <location code="WR051" />
    <location code="WR053" />
  </connector>
  <connector code="BI2" type="w2w">
    <location code="WR043" />
  </connector>
  <connector code="bT1" type="w2w">
    <location code="WR051" />
    <location code="WR053" />
  </connector>
  <connector code="bT2" type="w2w">
    <location code="WR051" />
    <location code="WR053" />
  </connector>
  <connector code="bT3" type="w2w">
    <location code="WR053" />
  </connector>
  <connector code="ca3" type="w2w">
    <location code="WR051" />
    <location code="WR053" />
  </connector>
  <connector code="ca4" type="w2w">
    <location code="WR051" />
    <location code="WR053" />
  </connector>
  <connector code="Ch1" type="w2w">
    <location code="WR043" />
  </connector>
  <connector code="DA1" type="w2w">
    <location code="WR043" />
  </connector>
  <connector code="db1" type="w2w">
    <location code="WR051" />
    <location code="WR053" />
  </connector>
  <connector code="eb2" type="w2w">
    <location code="WR051" />
    <location code="WR053" />
  </connector>
  <connector code="IA1" type="w2w">
    <location code="WR043" />
  </connector>
  <connector code="IA2" type="w2w">
    <location code="WR043" />
  </connector>
  <connector code="IC1" type="w2w">
    <location code="WR043" />
  </connector>
  <connector code="IC2" type="w2w">
    <location code="WR043" />
  </connector>
  <connector code="IC3" type="w2w">
    <location code="WR043" />
  </connector>
  <connector code="IL1" type="w2w">
    <location code="WR049" />
  </connector>
  <connector code="IL2" type="w2w">
    <location code="WR049" />
  </connector>
  <connector code="IL3" type="w2w">
    <location code="WR049" />
  </connector>
  <connector code="IL4" type="w2w">
    <location code="WR049" />
  </connector>
  <connector code="IN1" type="w2w">
    <location code="WR049" />
  </connector>
  <connector code="IS1" type="w2w">
    <location code="WR049" />
  </connector>
  <connector code="IS2" type="w2w">
    <location code="WR049" />
  </connector>
  <connector code="IS3" type="w2w">
    <location code="WR049" />
  </connector>
  <connector code="JK2" type="w2w">
    <location code="WR043" />
  </connector>
  <connector code="KI2" type="w2w">
    <location code="WR043" />
  </connector>
  <connector code="LI1" type="w2w">
    <location code="WR049" />
  </connector>
  <connector code="LM1" type="w2w">
    <location code="WR049" />
  </connector>
  <connector code="LS1" type="w2w">
    <location code="WR049" />
  </connector>
  <connector code="LS2" type="w2w">
    <location code="WR049" />
  </connector>
  <connector code="mA1" type="w2w">
    <location code="WR043" />
  </connector>
  <connector code="OI2" type="w2w">
    <location code="WR049" />
  </connector>
  <connector code="OI4" type="w2w">
    <location code="WR049" />
  </connector>
  <connector code="Oj1" type="w2w">
    <location code="WR051" />
    <location code="WR053" />
    <location code="WR055" />
    <location code="WR057" />
  </connector>
  <connector code="Oj2" type="w2w">
    <location code="WR051" />
    <location code="WR053" />
    <location code="WR055" />
    <location code="WR057" />
  </connector>
  <connector code="OL1" type="w2w">
    <location code="WR049" />
  </connector>
  <connector code="OL2" type="w2w">
    <location code="WR049" />
  </connector>
  <connector code="Pi1" type="w2w">
    <location code="WR051" />
    <location code="WR053" />
    <location code="WR055" />
    <location code="WR057" />
  </connector>
  <connector code="PI3" type="w2w">
    <location code="WR049" />
  </connector>
  <connector code="PL1" type="w2w">
    <location code="WR049" />
  </connector>
  <connector code="QU1" type="w2w">
    <location code="WR051" />
    <location code="WR055" />
  </connector>
  <connector code="RS1" type="w2w">
    <location code="WR051" />
    <location code="WR055" />
  </connector>
  <connector code="ST2" type="w2w">
    <location code="WR055" />
    <location code="WR057" />
  </connector>
  <connector code="ST3" type="w2w">
    <location code="WR055" />
    <location code="WR057" />
  </connector>
  <connector code="TS1" type="w2w">
    <location code="WR051" />
    <location code="WR053" />
  </connector>
  <connector code="TS2" type="w2w">
    <location code="WR051" />
    <location code="WR053" />
  </connector>
  <connector code="TS3" type="w2w">
    <location code="WR051" />
    <location code="WR053" />
  </connector>
  <connector code="TS4" type="w2w">
    <location code="WR051" />
    <location code="WR053" />
  </connector>
  <connector code="TV2" type="w2w">
    <location code="WR051" />
    <location code="WR053" />
  </connector>
  <connector code="TX1" type="w2w">
    <location code="WR053" />
    <location code="WR057" />
  </connector>
  <connector code="UI3" type="w2w">
    <location code="WR049" />
  </connector>
  <connector code="UI4" type="w2w">
    <location code="WR049" />
  </connector>
  <connector code="UI5" type="w2w">
    <location code="WR049" />
  </connector>
  <connector code="VT1" type="w2w">
    <location code="WR055" />
    <location code="WR057" />
  </connector>
  <connector code="WC2" type="w2w">
    <location code="WR053" />
    <location code="WR057" />
  </connector>
  <connector code="XT1" type="w2w">
    <location code="WR053" />
    <location code="WR057" />
  </connector>
  <connector code="YI2" type="w2w">
    <location code="WR049" />
  </connector>
  <connector code="YI3" type="w2w">
    <location code="WR049" />
  </connector>
  <connector code="YS4" type="w2w">
    <location code="WR053" />
  </connector>
  <connector code="1" type="jb">
    <location code="RL001" />
    <location code="RL008" ttl="RL001" />
  </connector>
  <connector code="2" type="jb">
    <location code="RL002" />
    <location code="RL003" />
    <location code="RL009" ttl="RL002" />
    <location code="RL016" ttl="RL003" />
  </connector>
  <connector code="3" type="jb">
    <location code="RL001" />
  </connector>
  <connector code="4" type="jb">
    <location code="RL001" />
  </connector>
  <connector code="JC-CANNO.1" type="jb">
    <location code="RL002" />
    <location code="RL003" />
  </connector>
  <connector code="JC-CANNO.2" type="jb">
    <location code="RL002" />
    <location code="RL003" />
  </connector>
  <connector code="JC-CANNO.4" type="jb">
    <location code="RL003" />
  </connector>
  <connector code="JC-CANNo.6" type="jb">
    <location code="RL002" />
  </connector>
  <connector code="3A" type="jbc">
    <location code="RL010" ttl="RL001" />
  </connector>
  <connector code="3B" type="jbc">
    <location code="RL010" ttl="RL001" />
  </connector>
  <connector code="3C" type="jbc">
    <location code="RL010" ttl="RL001" />
  </connector>
  <connector code="3D" type="jbc">
    <location code="RL010" ttl="RL001" />
  </connector>
  <connector code="3E" type="jbc">
    <location code="RL010" ttl="RL001" />
  </connector>
  <connector code="3F" type="jbc">
    <location code="RL010" ttl="RL001" />
  </connector>
  <connector code="3G" type="jbc">
    <location code="RL010" ttl="RL001" />
  </connector>
  <connector code="3H" type="jbc">
    <location code="RL010" ttl="RL001" />
  </connector>
  <connector code="3I" type="jbc">
    <location code="RL010" ttl="RL001" />
  </connector>
  <connector code="4A" type="jbc">
    <location code="RL011" ttl="RL001" />
  </connector>
  <connector code="4B" type="jbc">
    <location code="RL011" ttl="RL001" />
  </connector>
  <connector code="AA" type="gp">
    <location code="WR044" />
  </connector>
  <connector code="AC" type="gp">
    <location code="WR044" />
  </connector>
  <connector code="AD" type="gp">
    <location code="WR044" />
  </connector>
  <connector code="CA" type="gp">
    <location code="WR044" />
  </connector>
  <connector code="CB" type="gp">
    <location code="WR044" />
  </connector>
  <connector code="DA" type="gp">
    <location code="WR044" />
  </connector>
  <connector code="HA" type="gp">
    <location code="WR044" />
  </connector>
  <connector code="HB" type="gp">
    <location code="WR044" />
  </connector>
  <connector code="IA" type="gp">
    <location code="WR050" />
  </connector>
  <connector code="IC" type="gp">
    <location code="WR050" />
  </connector>
  <connector code="IE" type="gp">
    <location code="WR044" />
  </connector>
  <connector code="LA" type="gp">
    <location code="WR050" />
  </connector>
  <connector code="LB" type="gp">
    <location code="WR050" />
  </connector>
  <connector code="tA" type="gp">
    <location code="WR044" />
  </connector>
  <connector code="TA" type="gp">
    <location code="WR052" />
    <location code="WR054" />
  </connector>
  <connector code="TB" type="gp">
    <location code="WR056" />
    <location code="WR058" />
  </connector>
  <connector code="TC" type="gp">
    <location code="WR056" />
    <location code="WR058" />
  </connector>
  <connector code="FUSE1" type="rb" subcode="">
    <location code="RL009" ttl="RL002" />
    <location code="RL016" ttl="RL003" />
  </connector>
  <connector code="FUSE2" type="rb" subcode="">
    <location code="RL009" ttl="RL002" />
    <location code="RL016" ttl="RL003" />
  </connector>
  <connector code="FUSE3" type="rb" subcode="">
    <location code="RL009" ttl="RL002" />
    <location code="RL016" ttl="RL003" />
  </connector>
  <connector code="FUSE4" type="rb" subcode="">
    <location code="RL009" ttl="RL002" />
    <location code="RL016" ttl="RL003" />
  </connector>
  <connector code="FUSE5" type="rb" subcode="">
    <location code="RL009" ttl="RL002" />
    <location code="RL016" ttl="RL003" />
  </connector>
  <connector code="FUSE6" type="rb" subcode="">
    <location code="RL009" ttl="RL002" />
    <location code="RL016" ttl="RL003" />
  </connector>
  <connector code="FUSE7" type="rb" subcode="">
    <location code="RL009" ttl="RL002" />
    <location code="RL016" ttl="RL003" />
  </connector>
  <connector code="FUSE8" type="rb" subcode="">
    <location code="RL009" ttl="RL002" />
    <location code="RL016" ttl="RL003" />
  </connector>
  <connector code="FUSE9" type="rb" subcode="">
    <location code="RL009" ttl="RL002" />
    <location code="RL016" ttl="RL003" />
  </connector>
  <connector code="FUSE10" type="rb" subcode="">
    <location code="RL009" ttl="RL002" />
    <location code="RL016" ttl="RL003" />
  </connector>
  <connector code="FUSE11" type="rb" subcode="">
    <location code="RL009" ttl="RL002" />
    <location code="RL016" ttl="RL003" />
  </connector>
  <connector code="FUSE12" type="rb" subcode="">
    <location code="RL009" ttl="RL002" />
    <location code="RL016" ttl="RL003" />
  </connector>
  <connector code="FUSE13" type="rb" subcode="">
    <location code="RL009" ttl="RL002" />
    <location code="RL016" ttl="RL003" />
  </connector>
  <connector code="FUSE14" type="rb" subcode="">
    <location code="RL009" ttl="RL002" />
    <location code="RL016" ttl="RL003" />
  </connector>
  <connector code="FUSE15" type="rb" subcode="">
    <location code="RL009" ttl="RL002" />
    <location code="RL016" ttl="RL003" />
  </connector>
  <connector code="FUSE16" type="rb" subcode="">
    <location code="RL009" ttl="RL002" />
    <location code="RL016" ttl="RL003" />
  </connector>
  <connector code="FUSE17" type="rb" subcode="">
    <location code="RL009" ttl="RL002" />
    <location code="RL016" ttl="RL003" />
  </connector>
  <connector code="FUSE18" type="rb" subcode="">
    <location code="RL009" ttl="RL002" />
    <location code="RL016" ttl="RL003" />
  </connector>
  <connector code="FUSE19" type="rb" subcode="">
    <location code="RL009" ttl="RL002" />
    <location code="RL016" ttl="RL003" />
  </connector>
  <connector code="FUSE20" type="rb" subcode="">
    <location code="RL009" ttl="RL002" />
    <location code="RL016" ttl="RL003" />
  </connector>
  <connector code="FUSE21" type="rb" subcode="">
    <location code="RL009" ttl="RL002" />
    <location code="RL016" ttl="RL003" />
  </connector>
  <connector code="FUSE22" type="rb" subcode="">
    <location code="RL009" ttl="RL002" />
    <location code="RL016" ttl="RL003" />
  </connector>
  <connector code="FUSE23" type="rb" subcode="">
    <location code="RL009" ttl="RL002" />
    <location code="RL016" ttl="RL003" />
  </connector>
  <connector code="FUSE24" type="rb" subcode="">
    <location code="RL009" ttl="RL002" />
    <location code="RL016" ttl="RL003" />
  </connector>
  <connector code="FUSE25" type="rb" subcode="">
    <location code="RL009" ttl="RL002" />
    <location code="RL016" ttl="RL003" />
  </connector>
  <connector code="FUSE26" type="rb" subcode="">
    <location code="RL009" ttl="RL002" />
    <location code="RL016" ttl="RL003" />
  </connector>
  <connector code="FUSE27" type="rb" subcode="">
    <location code="RL009" ttl="RL002" />
    <location code="RL016" ttl="RL003" />
  </connector>
  <connector code="FUSE28" type="rb" subcode="">
    <location code="RL009" ttl="RL002" />
    <location code="RL016" ttl="RL003" />
  </connector>
  <connector code="FUSE29" type="rb" subcode="">
    <location code="RL009" ttl="RL002" />
    <location code="RL016" ttl="RL003" />
  </connector>
  <connector code="FUSE30" type="rb" subcode="">
    <location code="RL009" ttl="RL002" />
    <location code="RL016" ttl="RL003" />
  </connector>
  <connector code="FUSE31" type="rb" subcode="">
    <location code="RL009" ttl="RL002" />
    <location code="RL016" ttl="RL003" />
  </connector>
  <connector code="FUSE32" type="rb" subcode="">
    <location code="RL009" ttl="RL002" />
    <location code="RL016" ttl="RL003" />
  </connector>
  <connector code="FUSE33" type="rb" subcode="">
    <location code="RL009" ttl="RL002" />
    <location code="RL016" ttl="RL003" />
  </connector>
  <connector code="FUSE34" type="rb" subcode="">
    <location code="RL009" ttl="RL002" />
    <location code="RL016" ttl="RL003" />
  </connector>
  <connector code="FUSE35" type="rb" subcode="">
    <location code="RL010" ttl="RL001" />
  </connector>
  <connector code="FUSE36" type="rb" subcode="">
    <location code="RL010" ttl="RL001" />
  </connector>
  <connector code="FUSE37" type="rb" subcode="">
    <location code="RL010" ttl="RL001" />
  </connector>
  <connector code="FUSE38" type="rb" subcode="">
    <location code="RL010" ttl="RL001" />
  </connector>
  <connector code="FUSE39" type="rb" subcode="">
    <location code="RL010" ttl="RL001" />
  </connector>
  <connector code="FUSE40" type="rb" subcode="">
    <location code="RL010" ttl="RL001" />
  </connector>
  <connector code="FUSE41" type="rb" subcode="">
    <location code="RL010" ttl="RL001" />
  </connector>
  <connector code="FUSE42" type="rb" subcode="">
    <location code="RL010" ttl="RL001" />
  </connector>
  <connector code="FUSE43" type="rb" subcode="">
    <location code="RL010" ttl="RL001" />
  </connector>
  <connector code="FUSE44" type="rb" subcode="">
    <location code="RL011" ttl="RL001" />
  </connector>
  <connector code="FUSE45" type="rb" subcode="">
    <location code="RL011" ttl="RL001" />
  </connector>
  <connector code="FUSE46" type="rb" subcode="">
    <location code="RL011" ttl="RL001" />
  </connector>
  <connector code="FUSE47" type="rb" subcode="">
    <location code="RL011" ttl="RL001" />
  </connector>
  <connector code="FUSE48" type="rb" subcode="">
    <location code="RL011" ttl="RL001" />
  </connector>
  <connector code="FUSE49" type="rb" subcode="">
    <location code="RL011" ttl="RL001" />
  </connector>
  <connector code="FUSE50" type="rb" subcode="">
    <location code="RL011" ttl="RL001" />
  </connector>
  <connector code="FUSE51" type="rb" subcode="">
    <location code="RL011" ttl="RL001" />
  </connector>
  <connector code="FUSE52" type="rb" subcode="">
    <location code="RL011" ttl="RL001" />
  </connector>
  <connector code="FUSE53" type="rb" subcode="">
    <location code="RL011" ttl="RL001" />
  </connector>
  <connector code="FUSE54" type="rb" subcode="">
    <location code="RL011" ttl="RL001" />
  </connector>
  <connector code="FUSE55" type="rb" subcode="">
    <location code="RL011" ttl="RL001" />
  </connector>
  <connector code="FUSE56" type="rb" subcode="">
    <location code="RL011" ttl="RL001" />
  </connector>
  <connector code="FUSE57" type="rb" subcode="">
    <location code="RL011" ttl="RL001" />
  </connector>
</LocRefs>